{
  "swagger": "2.0",
  "info": {
    "title": "Auth Service API",
    "description": "Automatically generated swagger documentation for the Auth Service API",
    "version": "1.0.0"
  },
  "host": "localhost:6001",
  "basePath": "/api",
  "schemes": [
    "http"
  ],
  "consumes": [
    "application/json"
  ],
  "produces": [
    "application/json"
  ],
  "paths": {
    "/user-registration": {
      "post": {
        "description": "",
        "parameters": [
          {
            "name": "body",
            "in": "body",
            "schema": {
              "type": "object",
              "properties": {
                "name": {
                  "example": "any"
                },
                "email": {
                  "example": "any"
                }
              }
            }
          }
        ],
        "responses": {
          "200": {
            "description": "OK"
          },
          "400": {
            "description": "Bad Request"
          }
        }
      }
    },
    "/verify-user": {
      "post": {
        "description": "",
        "parameters": [
          {
            "name": "body",
            "in": "body",
            "schema": {
              "type": "object",
              "properties": {
                "email": {
                  "example": "any"
                },
                "otp": {
                  "example": "any"
                },
                "password": {
                  "example": "any"
                },
                "name": {
                  "example": "any"
                }
              }
            }
          }
        ],
        "responses": {
          "200": {
            "description": "OK"
          }
        }
      }
    }
  }
}